masspds2024/__init__.py
masspds2024/data.py
masspds2024-0.0.4.dist-info/LICENSE.txt
masspds2024-0.0.4.dist-info/METADATA
masspds2024-0.0.4.dist-info/WHEEL
masspds2024-0.0.4.dist-info/top_level.txt
masspds2024-0.0.4.dist-info/RECORD
