Metadata-Version: 2.1
Name: masspds2024
Version: 0.0.4
Summary: Package contains useful commands for mentee MaSSP DS 2024
Home-page: https://github/
Author: MaSSP Mathematics and Computer Science 2024
Author-email: nghi08122003@gmail.com
Project-URL: repository, https://github/
Classifier: Programming Language :: Python :: 3
Classifier: License :: OSI Approved :: MIT License
Classifier: Operating System :: OS Independent
Requires-Python: >=3.6
License-File: LICENSE.txt
